MANIFEST.in
README.txt
setup.cfg
setup.py
docs/HISTORY.txt
horae/__init__.py
horae.datetime.egg-info/PKG-INFO
horae.datetime.egg-info/SOURCES.txt
horae.datetime.egg-info/dependency_links.txt
horae.datetime.egg-info/entry_points.txt
horae.datetime.egg-info/namespace_packages.txt
horae.datetime.egg-info/not-zip-safe
horae.datetime.egg-info/requires.txt
horae.datetime.egg-info/top_level.txt
horae/datetime/__init__.py
horae/datetime/configure.zcml
horae/datetime/resource.py
horae/datetime/widget.py
horae/datetime/static/datetime.css
horae/datetime/static/datetime.js
horae/datetime/static/jquery.spinbox.js
horae/datetime/static/spinbox-down-hover.gif
horae/datetime/static/spinbox-down.gif
horae/datetime/static/spinbox-neutral.gif
horae/datetime/static/spinbox-up-hover.gif
horae/datetime/static/spinbox-up.gif