Metadata-Version: 1.0
Name: horae.datetime
Version: 1.0a1
Summary: zope.formlib datetime widget used by Horae
Home-page: UNKNOWN
Author: Simon Kaeser
Author-email: skaeser@raptus.com
License: GPL
Platform: UNKNOWN
Classifier: Programming Language :: Python
Classifier: Topic :: Software Development :: Libraries :: Python Modules
